odoo8_addon_mgmtsystem_manuals-8.0.1.1.0.99.dev5-py2.7-nspkg.pth
odoo8_addon_mgmtsystem_manuals-8.0.1.1.0.99.dev5.dist-info/DESCRIPTION.rst
odoo8_addon_mgmtsystem_manuals-8.0.1.1.0.99.dev5.dist-info/METADATA
odoo8_addon_mgmtsystem_manuals-8.0.1.1.0.99.dev5.dist-info/RECORD
odoo8_addon_mgmtsystem_manuals-8.0.1.1.0.99.dev5.dist-info/WHEEL
odoo8_addon_mgmtsystem_manuals-8.0.1.1.0.99.dev5.dist-info/metadata.json
odoo8_addon_mgmtsystem_manuals-8.0.1.1.0.99.dev5.dist-info/namespace_packages.txt
odoo8_addon_mgmtsystem_manuals-8.0.1.1.0.99.dev5.dist-info/top_level.txt
odoo_addons/mgmtsystem_manuals/__init__.py
odoo_addons/mgmtsystem_manuals/__openerp__.py
odoo_addons/mgmtsystem_manuals/data/document_page.xml
odoo_addons/mgmtsystem_manuals/i18n/de.po
odoo_addons/mgmtsystem_manuals/i18n/es.po
odoo_addons/mgmtsystem_manuals/i18n/fr.po
odoo_addons/mgmtsystem_manuals/i18n/hr.po
odoo_addons/mgmtsystem_manuals/i18n/mgmtsystem_manuals.pot
odoo_addons/mgmtsystem_manuals/i18n/nb.po
odoo_addons/mgmtsystem_manuals/i18n/pt_BR.po
odoo_addons/mgmtsystem_manuals/i18n/sl.po
odoo_addons/mgmtsystem_manuals/i18n/sv.po
odoo_addons/mgmtsystem_manuals/i18n/th.po
odoo_addons/mgmtsystem_manuals/i18n/vi.po
odoo_addons/mgmtsystem_manuals/migrations/7.0.1.0/pre-migration.py
odoo_addons/mgmtsystem_manuals/static/description/icon.png
odoo_addons/mgmtsystem_manuals/views/document_page.xml
